monitor_requests/__init__.py
monitor_requests/data.py
monitor_requests/output.py
monitor_requests/server.py
monitor_requests-2.1.1.dist-info/LICENSE
monitor_requests-2.1.1.dist-info/METADATA
monitor_requests-2.1.1.dist-info/WHEEL
monitor_requests-2.1.1.dist-info/entry_points.txt
monitor_requests-2.1.1.dist-info/top_level.txt
monitor_requests-2.1.1.dist-info/RECORD
