Metadata-Version: 2.1
Name: monitor-requests
Version: 2.1.1
Summary: Check remote calls via request
Home-page: https://github.com/danpozmanter/monitor_requests
Author: Dan Pozmanter
Author-email: UNKNOWN
License: BSD
Keywords: requests testing monitoring
Platform: UNKNOWN
Classifier: Development Status :: 5 - Production/Stable
Classifier: Intended Audience :: Developers
Classifier: License :: OSI Approved :: BSD License
Classifier: Natural Language :: English
Classifier: Operating System :: OS Independent
Classifier: Topic :: Software Development :: Libraries :: Python Modules
Classifier: Topic :: Software Development :: Testing
